omdb/__init__.py
omdb/omdb.py
tests/__init__.py
tests/test_omdb.py
omdbpy-0.1.12.dist-info/LICENSE
omdbpy-0.1.12.dist-info/METADATA
omdbpy-0.1.12.dist-info/WHEEL
omdbpy-0.1.12.dist-info/top_level.txt
omdbpy-0.1.12.dist-info/RECORD
