Metadata-Version: 2.1
Name: omdbpy
Version: 0.1.12
Summary: A minimalist Python wrapper for the Open Movie Database (OMDb) API (https://www.omdbapi.com/).
Home-page: https://github.com/blairg23/omdbpy
Author: Blair Gemmer
Author-email: blair@intelligen.technology
Maintainer: Blair Gemmer
Maintainer-email: blair@intelligen.technology
License: MIT
Project-URL: Source, https://github.com/blairg23/omdbpy
Project-URL: Tracker, https://github.com/blairg23/omdbpy/issues
Keywords: omdb api imdb movies television
Platform: any
Classifier: Development Status :: 2 - Pre-Alpha
Classifier: Environment :: Web Environment
Classifier: Intended Audience :: Developers
Classifier: License :: OSI Approved :: MIT License
Classifier: Operating System :: OS Independent
Classifier: Programming Language :: Python
Classifier: Programming Language :: Python :: 3
Classifier: Programming Language :: Python :: 3.6
Classifier: Programming Language :: Python :: 3.7
Requires-Dist: requests
Provides-Extra: testing
Requires-Dist: faker ; extra == 'testing'
Requires-Dist: pytest-cov ; extra == 'testing'
Requires-Dist: pytest ; extra == 'testing'
Requires-Dist: tox ; extra == 'testing'
